potatoscript/potatoConfig.py
python/CodeTemplate.py
python/pthonTemplate.py
python/pyTemplate.py
python/pypiTemplate.py
python/pythonTemplate.py
python/xTemplate.py
pthonTemplate-1.5.0.dist-info/METADATA
pthonTemplate-1.5.0.dist-info/WHEEL
pthonTemplate-1.5.0.dist-info/top_level.txt
pthonTemplate-1.5.0.dist-info/RECORD
