Metadata-Version: 2.1
Name: pthonTemplate
Version: 1.5.0
Summary: A simple Template for create python project
Author: ks lim
Author-email: kianseng.lim@sony.com
